arma_server_tools/__init__.py
arma_server_tools/arma_server.py
arma_server_tools/preset_parser.py
arma_server_tools/server_config.py
arma_server_tools/server_config_fields.yaml
arma_server_tools/workshop.py
arma_server_tools/yaml_tools.py
arma_server_tools-0.1.5.dist-info/entry_points.txt
arma_server_tools-0.1.5.dist-info/METADATA
arma_server_tools-0.1.5.dist-info/WHEEL
arma_server_tools-0.1.5.dist-info/RECORD
