Metadata-Version: 2.1
Name: arma_server_tools
Version: 0.1.5
Summary: 
Author: Ryan
Author-email: citizen.townshend@gmail.com
Requires-Python: >=3.12,<4.0
Classifier: Programming Language :: Python :: 3
Classifier: Programming Language :: Python :: 3.12
Requires-Dist: beautifulsoup4 (>=4.9.3,<5.0.0)
Requires-Dist: click (>=8.1.7,<9.0.0)
Requires-Dist: click-log (>=0.4.0,<0.5.0)
Requires-Dist: pyyaml (>=6.0.1,<7.0.0)
